[
  {
    "net": "JP",
    "sta": "JTM",
    "loc": "",
    "stalat": 40.789501,
    "stalon": 141.064667,
    "dist_km": 148.40020379595526
  },
  {
    "net": "JP",
    "sta": "JMM",
    "loc": "",
    "stalat": 37.868999,
    "stalon": 140.789673,
    "dist_km": 221.3773997349181
  },
  {
    "net": "II",
    "sta": "ERM",
    "loc": "00",
    "stalat": 42.015,
    "stalon": 143.1572,
    "dist_km": 282.35194835418616
  },
  {
    "net": "JP",
    "sta": "JEM",
    "loc": "",
    "stalat": 42.018501,
    "stalon": 143.153503,
    "dist_km": 282.60257751489524
  },
  {
    "net": "JP",
    "sta": "JEW",
    "loc": "",
    "stalat": 42.84267,
    "stalon": 141.446167,
    "dist_km": 358.09696198660754
  }
]